config_backup/ConfigBackup.py
config_backup/__init__.py
config_backup/admin.py
config_backup/apps.py
config_backup/backup.py
config_backup/exceptions.py
config_backup/git.py
config_backup/models.py
config_backup/management/__init__.py
config_backup/management/commands/__init__.py
config_backup/management/commands/config_backup.py
config_backup/management/commands/enable_scp.py
config_backup/management/commands/hostname.py
config_backup/management/commands/power_cycle.py
config_backup/migrations/0001_initial.py
config_backup/migrations/__init__.py
config_backup/switch_cli/__init__.py
config_backup/switch_cli/get_connection.py
config_backup/switch_cli/utils.py
config_backup/switch_cli/connections/__init__.py
config_backup/switch_cli/connections/exceptions.py
config_backup/switch_cli/connections/Cisco/CLI.py
config_backup/switch_cli/connections/Cisco/__init__.py
config_backup/switch_cli/connections/Comware/ComwareCLI.py
config_backup/switch_cli/connections/Comware/HP1910.py
config_backup/switch_cli/connections/Comware/__init__.py
config_backup/switch_cli/connections/HP/ProCurveCLI.py
config_backup/switch_cli/connections/HP/__init__.py
config_backup/switch_cli/connections/common/Connection.py
config_backup/switch_cli/connections/common/SwitchCli.py
config_backup/switch_cli/connections/common/__init__.py
config_backup/switch_cli/connections/common/ssh.py
config_backup/switch_cli/connections/common/telnet.py
django_switch_config_backup-1.1.dist-info/LICENSE
django_switch_config_backup-1.1.dist-info/METADATA
django_switch_config_backup-1.1.dist-info/WHEEL
django_switch_config_backup-1.1.dist-info/top_level.txt
django_switch_config_backup-1.1.dist-info/RECORD
